muvm/__init__.py
muvm/algorithms/__init__.py
muvm/algorithms/briarmbg.py
muvm/algorithms/depth_to_image_pipeline.py
muvm/algorithms/image_text_to_image.py
muvm/algorithms/image_variation.py
muvm/algorithms/ldm_super_resolution.py
muvm/algorithms/scheduling_dpmsolver_multistep_inject.py
muvm/algorithms/semantic_stable_diffusion_img2img.py
muvm/algorithms/utils.py
muvm/backend/__init__.py
muvm/backend/api_classes.py
muvm/backend/api_handeler.py
MuVM_python-0.0.1.dist-info/LICENSE
MuVM_python-0.0.1.dist-info/METADATA
MuVM_python-0.0.1.dist-info/WHEEL
MuVM_python-0.0.1.dist-info/top_level.txt
MuVM_python-0.0.1.dist-info/RECORD
