Metadata-Version: 2.1
Name: MuVM-python
Version: 0.0.1
Summary: With MuVM (MultiVisionModels) talk to your Images!
Author-email: Erfan Zare Chavoshi <Erfanzare810@gmail.com>
License: Apache-2.0
Keywords: Torch,Deep Learning,Machine Learning,Diffusers
Classifier: Development Status :: 3 - Alpha
Classifier: Intended Audience :: Developers
Classifier: Topic :: Scientific/Engineering :: Artificial Intelligence
Classifier: License :: OSI Approved :: Apache Software License
Classifier: Programming Language :: Python :: 3
Classifier: Programming Language :: Python :: 3.8
Classifier: Programming Language :: Python :: 3.9
Classifier: Programming Language :: Python :: 3.10
Classifier: Programming Language :: Python :: 3.11
Classifier: Programming Language :: Python :: 3.12
Requires-Python: >=3.8
License-File: LICENSE
Requires-Dist: diffusers >=0.26.2
Requires-Dist: torch
Requires-Dist: transformers
